jsonschema_test/__init__.py
jsonschema_test/schema.json
jsonschema_test-1.1.0.dist-info/DESCRIPTION.rst
jsonschema_test-1.1.0.dist-info/METADATA
jsonschema_test-1.1.0.dist-info/RECORD
jsonschema_test-1.1.0.dist-info/WHEEL
jsonschema_test-1.1.0.dist-info/entry_points.txt
jsonschema_test-1.1.0.dist-info/metadata.json
jsonschema_test-1.1.0.dist-info/top_level.txt
