Metadata-Version: 2.0
Name: jsonschema-test
Version: 1.1.0
Summary: A tool for writing and running tests against a given JSON Schema.
Home-page: https://github.com/kylef/jsonschema-test
Author: Kyle Fuller
Author-email: kyle@fuller.li
License: BSD
Platform: UNKNOWN
Classifier: Development Status :: 5 - Production/Stable
Classifier: Programming Language :: Python :: 2
Classifier: Programming Language :: Python :: 2.7
Classifier: Programming Language :: Python :: 3
Classifier: Programming Language :: Python :: 3.2
Classifier: Programming Language :: Python :: 3.3
Classifier: Programming Language :: Python :: 3.4
Classifier: License :: OSI Approved :: BSD License
Requires-Dist: jsonschema
